odoo/addons/vault_share/README.rst
odoo/addons/vault_share/__init__.py
odoo/addons/vault_share/__manifest__.py
odoo/addons/vault_share/controllers/__init__.py
odoo/addons/vault_share/controllers/main.py
odoo/addons/vault_share/data/ir_cron.xml
odoo/addons/vault_share/i18n/es.po
odoo/addons/vault_share/i18n/vault_share.pot
odoo/addons/vault_share/models/__init__.py
odoo/addons/vault_share/models/res_company.py
odoo/addons/vault_share/models/res_config_settings.py
odoo/addons/vault_share/models/vault_share.py
odoo/addons/vault_share/models/vault_share_log.py
odoo/addons/vault_share/readme/CONTRIBUTORS.rst
odoo/addons/vault_share/readme/DESCRIPTION.rst
odoo/addons/vault_share/security/ir.model.access.csv
odoo/addons/vault_share/security/ir_rule.xml
odoo/addons/vault_share/static/description/icon.png
odoo/addons/vault_share/static/description/index.html
odoo/addons/vault_share/static/src/js/vault_fields.js
odoo/addons/vault_share/static/src/js/vault_share.js
odoo/addons/vault_share/static/src/js/vault_share_widget.js
odoo/addons/vault_share/static/src/js/vault_utils.js
odoo/addons/vault_share/static/src/scss/vault_share.scss
odoo/addons/vault_share/static/src/xml/templates.xml
odoo/addons/vault_share/tests/__init__.py
odoo/addons/vault_share/tests/test_share.py
odoo/addons/vault_share/views/assets.xml
odoo/addons/vault_share/views/menuitems.xml
odoo/addons/vault_share/views/res_config_settings_views.xml
odoo/addons/vault_share/views/templates.xml
odoo/addons/vault_share/views/vault_share_views.xml
odoo13_addon_vault_share-13.0.1.0.1.dist-info/METADATA
odoo13_addon_vault_share-13.0.1.0.1.dist-info/WHEEL
odoo13_addon_vault_share-13.0.1.0.1.dist-info/top_level.txt
odoo13_addon_vault_share-13.0.1.0.1.dist-info/RECORD
